Metadata-Version: 2.4
Name: package-grecco
Version: 0.0.1
Summary: My short description
Home-page: https://github.com/PedroHFGrecco/simple-package-template.git
Author: PedroGrecco
Author-email: pedrohenrique.ferreiragrecco@gmail.com
Requires-Python: >=3.8
Dynamic: author
Dynamic: author-email
Dynamic: description
Dynamic: description-content-type
Dynamic: home-page
Dynamic: requires-python
Dynamic: summary
